yaskill/__init__.py
yaskill-0.0.0.dist-info/WHEEL
yaskill-0.0.0.dist-info/entry_points.txt
yaskill-0.0.0.dist-info/METADATA
yaskill-0.0.0.dist-info/RECORD
