Metadata-Version: 2.3
Name: yaskill
Version: 0.0.0
Summary: Yet Another agent Skills implementation
Author: Tang Ziya
Author-email: Tang Ziya <tcztzy@gmail.Com>
Requires-Python: >=3.12
